odoo/addons/stock_override_procurement/README.rst
odoo/addons/stock_override_procurement/__init__.py
odoo/addons/stock_override_procurement/__manifest__.py
odoo/addons/stock_override_procurement/i18n/it.po
odoo/addons/stock_override_procurement/i18n/stock_override_procurement.pot
odoo/addons/stock_override_procurement/models/__init__.py
odoo/addons/stock_override_procurement/models/procurement_group.py
odoo/addons/stock_override_procurement/readme/CONTRIBUTORS.rst
odoo/addons/stock_override_procurement/readme/DESCRIPTION.rst
odoo/addons/stock_override_procurement/readme/USAGE.rst
odoo/addons/stock_override_procurement/static/description/icon.png
odoo/addons/stock_override_procurement/static/description/index.html
odoo/addons/stock_override_procurement/tests/__init__.py
odoo/addons/stock_override_procurement/tests/test_stock_override_procurement.py
odoo_addon_stock_override_procurement-16.0.1.0.0.5.dist-info/METADATA
odoo_addon_stock_override_procurement-16.0.1.0.0.5.dist-info/WHEEL
odoo_addon_stock_override_procurement-16.0.1.0.0.5.dist-info/top_level.txt
odoo_addon_stock_override_procurement-16.0.1.0.0.5.dist-info/RECORD
